megickfilebrowse/__init__.py
megickfilebrowse/megickfilebrowse.py
megickfilebrowse/megickfilebrowse.pyi
megickfilebrowse/templates/component/index.js
megickfilebrowse/templates/component/style.css
megickfilebrowse/templates/example/index.js
megickfilebrowse/templates/example/style.css
megickfilebrowse-0.0.4.dist-info/METADATA
megickfilebrowse-0.0.4.dist-info/WHEEL
megickfilebrowse-0.0.4.dist-info/licenses/LICENSE
megickfilebrowse-0.0.4.dist-info/RECORD
