Metadata-Version: 2.3
Name: megickfilebrowse
Version: 0.0.4
Summary: An extension of Gradio's FileExplorer, with more customization.
Project-URL: repository, https://github.com/Mejikan/megickfilebrowse
Author-email: Mejikan <mejikan@example.com>
License-Expression: Apache-2.0
License-File: LICENSE
Keywords: file,gradio-custom-component,gradio-template-FileExplorer
Classifier: Development Status :: 3 - Alpha
Classifier: License :: OSI Approved :: Apache Software License
Classifier: Operating System :: OS Independent
Classifier: Programming Language :: Python :: 3
Classifier: Programming Language :: Python :: 3 :: Only
Classifier: Programming Language :: Python :: 3.10
Classifier: Programming Language :: Python :: 3.11
Classifier: Topic :: Scientific/Engineering
Classifier: Topic :: Scientific/Engineering :: Artificial Intelligence
Classifier: Topic :: Scientific/Engineering :: Visualization
Requires-Python: >=3.10
Requires-Dist: gradio<5.0,>=4.0
Provides-Extra: dev
Requires-Dist: build; extra == 'dev'
Requires-Dist: twine; extra == 'dev'
